LICENSE
MANIFEST.in
README.rst
helga_pull_requests.py
setup.py
helga_pull_requests.egg-info/PKG-INFO
helga_pull_requests.egg-info/SOURCES.txt
helga_pull_requests.egg-info/dependency_links.txt
helga_pull_requests.egg-info/entry_points.txt
helga_pull_requests.egg-info/top_level.txt
helga_pull_requests.egg-info/zip-safe