Metadata-Version: 1.1
Name: helga-pull-requests
Version: 0.0.1
Summary: A helga plugin to quickly link to github pull requests.
Home-page: https://github.com/shaunduncan/helga-pull-requests
Author: Shaun Duncan
Author-email: shaun.duncan@gmail.com
License: UNKNOWN
Keywords: helga github pull requests
Platform: UNKNOWN
Classifier: Development Status :: 4 - Beta
Classifier: Topic :: Communications :: Chat :: Internet Relay Chat
Classifier: Framework :: Twisted
Classifier: License :: OSI Approved :: MIT License
Classifier: Operating System :: OS Independent
Classifier: Programming Language :: Python
Classifier: Programming Language :: Python :: 2
Classifier: Programming Language :: Python :: 2.6
Classifier: Programming Language :: Python :: 2.7
Classifier: Topic :: Software Development :: Libraries :: Python Modules
